gucken_image_reader-1.1.3.dist-info/licenses/LICENSE
mcp_image_reader/__init__.py
mcp_image_reader/__main__.py
mcp_image_reader/server.py
gucken_image_reader-1.1.3.dist-info/METADATA
gucken_image_reader-1.1.3.dist-info/WHEEL
gucken_image_reader-1.1.3.dist-info/entry_points.txt
gucken_image_reader-1.1.3.dist-info/top_level.txt
gucken_image_reader-1.1.3.dist-info/RECORD
